fasterrisk/__init__.py
fasterrisk/base_model.py
fasterrisk/binarization_util.py
fasterrisk/fasterrisk.py
fasterrisk/fonts/NotoSansMath-Regular.ttf
fasterrisk/fonts/Oswald-Medium.ttf
fasterrisk/fonts/RobotoCondensed-Regular.ttf
fasterrisk/rounding.py
fasterrisk/score_visual.py
fasterrisk/sparseBeamSearch.py
fasterrisk/sparseDiversePool.py
fasterrisk/utils.py
fasterrisk/wrapper.py
fasterrisk-0.1.10.dist-info/LICENSE
fasterrisk-0.1.10.dist-info/METADATA
fasterrisk-0.1.10.dist-info/WHEEL
fasterrisk-0.1.10.dist-info/RECORD
