Metadata-Version: 2.1
Name: fasterrisk
Version: 0.1.10
Summary: Create sparse and accurate risk scoring systems!
Home-page: https://pypi.org/project/fasterrisk/
License: BSD 3-Clause
Author: Jiachang Liu
Author-email: jiachang.liu@duke.edu
Maintainer: Jiachang Liu
Maintainer-email: jiachang.liu@duke.edu
Requires-Python: >=3.8,<4.0
Classifier: License :: Other/Proprietary License
Classifier: Programming Language :: Python :: 3
Classifier: Programming Language :: Python :: 3.8
Classifier: Programming Language :: Python :: 3.9
Classifier: Programming Language :: Python :: 3.10
Classifier: Programming Language :: Python :: 3.11
Classifier: Programming Language :: Python :: 3.12
Requires-Dist: matplotlib (==3.7.2)
Requires-Dist: numpy (>=1.23.3,<2.0.0)
Requires-Dist: pandas (==1.5.2)
Requires-Dist: pillow (==9.4.0)
Requires-Dist: requests (>=2.28.1,<3.0.0)
Requires-Dist: scikit-learn (==1.2.0)
Project-URL: Documentation, https://fasterrisk.readthedocs.io/en/latest/
Project-URL: Repository, https://github.com/jiachangliu/FasterRisk
